nrn/__init__.py
nrn/models/__init__.py
nrn/models/brn_classifier.py
nrn/models/base/__init__.py
nrn/models/base/boosted_brn.py
nrn/models/base/brn.py
nrn/models/base/pruningrn.py
nrn/models/base/rn.py
nrn/models/mixins/__init__.py
nrn/models/mixins/_base_mixin.py
nrn/models/mixins/classifier.py
nrn/modules/__init__.py
nrn/modules/brn.py
nrn/nn/__init__.py
nrn/nn/blocks.py
nrn/nn/predicates.py
nrn/nn/utils.py
nrn/nn/base/__init__.py
nrn/nn/base/_core.py
nrn/nn/base/blocks.py
nrn/nn/base/constants.py
nrn/nn/base/predicates.py
nrn/nn/base/utils.py
nrn/sklogic/__init__.py
nrn/sklogic/base/__init__.py
nrn/sklogic/base/base_estimator.py
nrn/sklogic/classifiers/RNRNClassifier.py
nrn/sklogic/classifiers/__init__.py
nrn/sklogic/datasets/__init__.py
nrn/sklogic/datasets/simple_dataset.py
nrn/sklogic/regressors/RNRNRegressor.py
nrn/sklogic/regressors/__init__.py
nrn/utils/__init__.py
nrn/utils/distributed.py
nrn/utils/mic.py
nrn/utils/operations.py
nrn/utils/explanations/__init__.py
nrn/utils/explanations/explanations.py
nrn/utils/explanations/simplification.py
nrn/utils/trainers/__init__.py
nrn/utils/trainers/banditnrntrainer.py
nrn/utils/trainers/boostedbanditnrntrainer.py
nrn/utils/trainers/base/__init__.py
nrn/utils/trainers/base/basetrainer.py
nrn_beta-0.1.12.dist-info/licenses/LICENSE
nrn_beta-0.1.12.dist-info/METADATA
nrn_beta-0.1.12.dist-info/WHEEL
nrn_beta-0.1.12.dist-info/top_level.txt
nrn_beta-0.1.12.dist-info/RECORD
