Metadata-Version: 2.4
Name: nrn-beta
Version: 0.1.12
Summary: A PyTorch framework for rapidly developing Neural Reasoning Networks.
Author: Anonymous
Classifier: Programming Language :: Python :: 3
Classifier: Operating System :: OS Independent
Requires-Python: >=3.6
License-File: LICENSE
Requires-Dist: torch>=2.0.0
Requires-Dist: numpy<2.0.0,>=1.25.0
Requires-Dist: pandas>=2.0.2
Requires-Dist: scipy>=1.10.1
Requires-Dist: scikit-learn>=1.2.2
Requires-Dist: pytest>=7.4.0
Requires-Dist: pytest-cov>=4.1.0
Requires-Dist: pytorch_optimizer>=2.12.0
Requires-Dist: torchvision>=0.16
Requires-Dist: xgboost>=2.0.2
Requires-Dist: setuptools>=69.0.2
Requires-Dist: cvxpy>=1.5.3
Requires-Dist: aix360>=0.3.0
Dynamic: author
Dynamic: classifier
Dynamic: license-file
Dynamic: requires-dist
Dynamic: requires-python
Dynamic: summary
